hdm2/__init__.py
hdm2/example_usage.py
hdm2/model.py
hdm2/data/__init__.py
hdm2/data/process_text.py
hdm2/models/__init__.py
hdm2/models/common_knowledge.py
hdm2/models/context_knowledge.py
hdm2/utils/__init__.py
hdm2/utils/debug_utils.py
hdm2/utils/load_models.py
hdm2/utils/model_utils.py
hdm2/utils/process_output.py
hdm2/utils/render_utils.py
hdm2-0.7.0.dist-info/licenses/LICENSE
hdm2-0.7.0.dist-info/METADATA
hdm2-0.7.0.dist-info/WHEEL
hdm2-0.7.0.dist-info/top_level.txt
hdm2-0.7.0.dist-info/RECORD
