Metadata-Version: 2.4
Name: hdm2
Version: 0.7.0
Summary: A tool for detecting and quantifying hallucinations in LLM responses through context and common knowledge verification
Home-page: https://github.com/aimonlabs/hallucination-detection-model
Author: Bibek Paudel
Author-email: bibek@aimon.ai
Project-URL: Bug Tracker, https://github.com/aimonlabs/hallucination-detection-model/issues
Classifier: Programming Language :: Python :: 3
Classifier: Operating System :: OS Independent
Requires-Python: >=3.8
License-File: LICENSE
Requires-Dist: torch>=2.0.0
Requires-Dist: transformers>=4.30.0
Requires-Dist: peft>=0.4.0
Requires-Dist: bitsandbytes>=0.40.0
Requires-Dist: nltk>=3.8.0
Requires-Dist: numpy>=1.22.0
Requires-Dist: huggingface_hub>=0.16.0
Requires-Dist: safetensors>=0.3.0
Requires-Dist: tqdm>=4.65.0
Provides-Extra: gpu
Requires-Dist: accelerate; extra == "gpu"
Dynamic: author
Dynamic: author-email
Dynamic: classifier
Dynamic: description
Dynamic: description-content-type
Dynamic: home-page
Dynamic: license-file
Dynamic: project-url
Dynamic: provides-extra
Dynamic: requires-dist
Dynamic: requires-python
Dynamic: summary
